asyncio_fast_portscanner/__init__.py
asyncio_fast_portscanner/asyncio_fast_portscanner.py
asyncio_fast_portscanner/cli.py
asyncio_fast_portscanner-0.0.2.dist-info/AUTHORS.rst
asyncio_fast_portscanner-0.0.2.dist-info/LICENSE
asyncio_fast_portscanner-0.0.2.dist-info/METADATA
asyncio_fast_portscanner-0.0.2.dist-info/WHEEL
asyncio_fast_portscanner-0.0.2.dist-info/entry_points.txt
asyncio_fast_portscanner-0.0.2.dist-info/top_level.txt
asyncio_fast_portscanner-0.0.2.dist-info/RECORD
