Metadata-Version: 2.1
Name: asyncio-fast-portscanner
Version: 0.0.2
Summary: Get your active host list in N * timeout fixed time
Home-page: https://github.com/Razikus/asyncio_fast_portscanner
Author: Adam Raźniewski
Author-email: adam@razniewski.eu
License: MIT license
Keywords: asyncio_fast_portscanner
Platform: UNKNOWN
Classifier: Development Status :: 2 - Pre-Alpha
Classifier: Intended Audience :: Developers
Classifier: License :: OSI Approved :: MIT License
Classifier: Natural Language :: English
Classifier: Programming Language :: Python :: 3
Classifier: Programming Language :: Python :: 3.5
Classifier: Programming Language :: Python :: 3.6
Classifier: Programming Language :: Python :: 3.7
Requires-Python: >=3.5, !=3.0.*, !=3.1.*, !=3.2.*, !=3.3.*, !=3.4.*
Requires-Dist: Click (>=7.0)
Requires-Dist: asyncio (==3.4.3)
